{
  "NOM.INFORM.SING": {
    "type": "pronoun",
    "english_case": "*",
    "aligned_case": "Nom",
    "english_form": "you",
    "aligned_form": "ty",
    "english_coref_pos": "",
    "aligned_coref_gender": "",
    "aligned_coref_number": "",
    "aligned_coref_pos": "",
    "requires_coref": "false"
  },
  "ACC.INFORM.SING": {
    "type": "pronoun",
    "english_case": "*",
    "aligned_case": "Acc",
    "english_form": "you",
    "aligned_form": "ciebie",
    "english_coref_pos": "",
    "aligned_coref_gender": "",
    "aligned_coref_number": "",
    "aligned_coref_pos": "",
    "requires_coref": "false"
  },
  "ACC.INFORM.SING.ALT1": {
    "type": "pronoun",
    "english_case": "*",
    "aligned_case": "Acc",
    "english_form": "you",
    "aligned_form": "ci\u0119",
    "english_coref_pos": "",
    "aligned_coref_gender": "",
    "aligned_coref_number": "",
    "aligned_coref_pos": "",
    "requires_coref": "false"
  },
  "GEN.INFORM.SING": {
    "type": "pronoun",
    "english_case": "*",
    "aligned_case": "Gen",
    "english_form": "you",
    "aligned_form": "ciebie",
    "english_coref_pos": "",
    "aligned_coref_gender": "",
    "aligned_coref_number": "",
    "aligned_coref_pos": "",
    "requires_coref": "false"
  },
  "GEN.INFORM.SING.ALT1": {
    "type": "pronoun",
    "english_case": "*",
    "aligned_case": "Gen",
    "english_form": "you",
    "aligned_form": "ci\u0119",
    "english_coref_pos": "",
    "aligned_coref_gender": "",
    "aligned_coref_number": "",
    "aligned_coref_pos": "",
    "requires_coref": "false"
  },
  "LOC.INFORM.SING": {
    "type": "pronoun",
    "english_case": "*",
    "aligned_case": "Loc",
    "english_form": "you",
    "aligned_form": "tobie",
    "english_coref_pos": "",
    "aligned_coref_gender": "",
    "aligned_coref_number": "",
    "aligned_coref_pos": "",
    "requires_coref": "false"
  },
  "DAT.INFORM.SING": {
    "type": "pronoun",
    "english_case": "*",
    "aligned_case": "Dat",
    "english_form": "you",
    "aligned_form": "tobie",
    "english_coref_pos": "",
    "aligned_coref_gender": "",
    "aligned_coref_number": "",
    "aligned_coref_pos": "",
    "requires_coref": "false"
  },
  "DAT.INFORM.SING.ALT1": {
    "type": "pronoun",
    "english_case": "*",
    "aligned_case": "Dat",
    "english_form": "you",
    "aligned_form": "ci",
    "english_coref_pos": "",
    "aligned_coref_gender": "",
    "aligned_coref_number": "",
    "aligned_coref_pos": "",
    "requires_coref": "false"
  },
  "INS.INFORM.SING": {
    "type": "pronoun",
    "english_case": "*",
    "aligned_case": "Dat",
    "english_form": "you",
    "aligned_form": "tob\u0105",
    "english_coref_pos": "",
    "aligned_coref_gender": "",
    "aligned_coref_number": "",
    "aligned_coref_pos": "",
    "requires_coref": "false"
  },
  "NOM.INFORM.PLUR": {
    "type": "pronoun",
    "english_case": "*",
    "aligned_case": "Nom",
    "english_form": "you",
    "aligned_form": "wy",
    "english_coref_pos": "",
    "aligned_coref_gender": "",
    "aligned_coref_number": "",
    "aligned_coref_pos": "",
    "requires_coref": "false"
  },
  "ACC.INFORM.PLUR": {
    "type": "pronoun",
    "english_case": "*",
    "aligned_case": "Acc",
    "english_form": "you",
    "aligned_form": "was",
    "english_coref_pos": "",
    "aligned_coref_gender": "",
    "aligned_coref_number": "",
    "aligned_coref_pos": "",
    "requires_coref": "false"
  },
  "GEN.INFORM.PLUR": {
    "type": "pronoun",
    "english_case": "*",
    "aligned_case": "Gen",
    "english_form": "you",
    "aligned_form": "was",
    "english_coref_pos": "",
    "aligned_coref_gender": "",
    "aligned_coref_number": "",
    "aligned_coref_pos": "",
    "requires_coref": "false"
  },
  "LOC.INFORM.PLUR": {
    "type": "pronoun",
    "english_case": "*",
    "aligned_case": "Loc",
    "english_form": "you",
    "aligned_form": "was",
    "english_coref_pos": "",
    "aligned_coref_gender": "",
    "aligned_coref_number": "",
    "aligned_coref_pos": "",
    "requires_coref": "false"
  },
  "DAT.INFORM.PLUR": {
    "type": "pronoun",
    "english_case": "*",
    "aligned_case": "Dat",
    "english_form": "you",
    "aligned_form": "wam",
    "english_coref_pos": "",
    "aligned_coref_gender": "",
    "aligned_coref_number": "",
    "aligned_coref_pos": "",
    "requires_coref": "false"
  },
  "INS.INFORM.PLUR": {
    "type": "pronoun",
    "english_case": "*",
    "aligned_case": "Ins",
    "english_form": "you",
    "aligned_form": "wami",
    "english_coref_pos": "",
    "aligned_coref_gender": "",
    "aligned_coref_number": "",
    "aligned_coref_pos": "",
    "requires_coref": "false"
  },
  "NOM.FORM.SING.FEM": {
    "type": "pronoun",
    "english_case": "*",
    "aligned_case": "Nom",
    "english_form": "you",
    "aligned_form": "pani",
    "english_coref_pos": "",
    "aligned_coref_gender": "",
    "aligned_coref_number": "",
    "aligned_coref_pos": "",
    "requires_coref": "false"
  },
  "ACC.FORM.SING.FEM": {
    "type": "pronoun",
    "english_case": "*",
    "aligned_case": "Acc",
    "english_form": "you",
    "aligned_form": "pani\u0105",
    "english_coref_pos": "",
    "aligned_coref_gender": "",
    "aligned_coref_number": "",
    "aligned_coref_pos": "",
    "requires_coref": "false"
  },
  "GEN.FORM.SING.FEM": {
    "type": "pronoun",
    "english_case": "*",
    "aligned_case": "Gen",
    "english_form": "you",
    "aligned_form": "pani",
    "english_coref_pos": "",
    "aligned_coref_gender": "",
    "aligned_coref_number": "",
    "aligned_coref_pos": "",
    "requires_coref": "false"
  },
  "LOC.FORM.SING.FEM": {
    "type": "pronoun",
    "english_case": "*",
    "aligned_case": "Loc",
    "english_form": "you",
    "aligned_form": "pani",
    "english_coref_pos": "",
    "aligned_coref_gender": "",
    "aligned_coref_number": "",
    "aligned_coref_pos": "",
    "requires_coref": "false"
  },
  "DAT.FORM.SING.FEM": {
    "type": "pronoun",
    "english_case": "*",
    "aligned_case": "Dat",
    "english_form": "you",
    "aligned_form": "pani",
    "english_coref_pos": "",
    "aligned_coref_gender": "",
    "aligned_coref_number": "",
    "aligned_coref_pos": "",
    "requires_coref": "false"
  },
  "INS.FORM.SING.FEM": {
    "type": "pronoun",
    "english_case": "*",
    "aligned_case": "Ins",
    "english_form": "you",
    "aligned_form": "pani\u0105",
    "english_coref_pos": "",
    "aligned_coref_gender": "",
    "aligned_coref_number": "",
    "aligned_coref_pos": "",
    "requires_coref": "false"
  },
  "NOM.FORM.SING.MASC": {
    "type": "pronoun",
    "english_case": "*",
    "aligned_case": "Nom",
    "english_form": "you",
    "aligned_form": "pan",
    "english_coref_pos": "",
    "aligned_coref_gender": "",
    "aligned_coref_number": "",
    "aligned_coref_pos": "",
    "requires_coref": "false"
  },
  "ACC.FORM.SING.MASC": {
    "type": "pronoun",
    "english_case": "*",
    "aligned_case": "Acc",
    "english_form": "you",
    "aligned_form": "pana",
    "english_coref_pos": "",
    "aligned_coref_gender": "",
    "aligned_coref_number": "",
    "aligned_coref_pos": "",
    "requires_coref": "false"
  },
  "GEN.FORM.SING.MASC": {
    "type": "pronoun",
    "english_case": "*",
    "aligned_case": "Gen",
    "english_form": "you",
    "aligned_form": "pana",
    "english_coref_pos": "",
    "aligned_coref_gender": "",
    "aligned_coref_number": "",
    "aligned_coref_pos": "",
    "requires_coref": "false"
  },
  "LOC.FORM.SING.MASC": {
    "type": "pronoun",
    "english_case": "*",
    "aligned_case": "Loc",
    "english_form": "you",
    "aligned_form": "panu",
    "english_coref_pos": "",
    "aligned_coref_gender": "",
    "aligned_coref_number": "",
    "aligned_coref_pos": "",
    "requires_coref": "false"
  },
  "DAT.FORM.SING.MASC": {
    "type": "pronoun",
    "english_case": "*",
    "aligned_case": "Dat",
    "english_form": "you",
    "aligned_form": "panu",
    "english_coref_pos": "",
    "aligned_coref_gender": "",
    "aligned_coref_number": "",
    "aligned_coref_pos": "",
    "requires_coref": "false"
  },
  "INS.FORM.SING.MASC": {
    "type": "pronoun",
    "english_case": "*",
    "aligned_case": "Ins",
    "english_form": "you",
    "aligned_form": "panem",
    "english_coref_pos": "",
    "aligned_coref_gender": "",
    "aligned_coref_number": "",
    "aligned_coref_pos": "",
    "requires_coref": "false"
  },
  "NOM.FORM.PLUR.MASC": {
    "type": "pronoun",
    "english_case": "*",
    "aligned_case": "Nom",
    "english_form": "you",
    "aligned_form": "panowie",
    "english_coref_pos": "",
    "aligned_coref_gender": "",
    "aligned_coref_number": "",
    "aligned_coref_pos": "",
    "requires_coref": "false"
  },
  "ACC.FORM.PLUR.MASC": {
    "type": "pronoun",
    "english_case": "*",
    "aligned_case": "Acc",
    "english_form": "you",
    "aligned_form": "pan\u00f3w",
    "english_coref_pos": "",
    "aligned_coref_gender": "",
    "aligned_coref_number": "",
    "aligned_coref_pos": "",
    "requires_coref": "false"
  },
  "GEN.FORM.PLUR.MASC": {
    "type": "pronoun",
    "english_case": "*",
    "aligned_case": "Gen",
    "english_form": "you",
    "aligned_form": "pan\u00f3w",
    "english_coref_pos": "",
    "aligned_coref_gender": "",
    "aligned_coref_number": "",
    "aligned_coref_pos": "",
    "requires_coref": "false"
  },
  "LOC.FORM.PLUR.MASC": {
    "type": "pronoun",
    "english_case": "*",
    "aligned_case": "Loc",
    "english_form": "you",
    "aligned_form": "panach",
    "english_coref_pos": "",
    "aligned_coref_gender": "",
    "aligned_coref_number": "",
    "aligned_coref_pos": "",
    "requires_coref": "false"
  },
  "DAT.FORM.PLUR.MASC": {
    "type": "pronoun",
    "english_case": "*",
    "aligned_case": "Dat",
    "english_form": "you",
    "aligned_form": "panom",
    "english_coref_pos": "",
    "aligned_coref_gender": "",
    "aligned_coref_number": "",
    "aligned_coref_pos": "",
    "requires_coref": "false"
  },
  "INS.FORM.PLUR.MASC": {
    "type": "pronoun",
    "english_case": "*",
    "aligned_case": "Ins",
    "english_form": "you",
    "aligned_form": "panami",
    "english_coref_pos": "",
    "aligned_coref_gender": "",
    "aligned_coref_number": "",
    "aligned_coref_pos": "",
    "requires_coref": "false"
  },
  "NOM.FORM.PLUR.FEM": {
    "type": "pronoun",
    "english_case": "*",
    "aligned_case": "Nom",
    "english_form": "you",
    "aligned_form": "panie",
    "english_coref_pos": "",
    "aligned_coref_gender": "",
    "aligned_coref_number": "",
    "aligned_coref_pos": "",
    "requires_coref": "false"
  },
  "ACC.FORM.PLUR.FEM": {
    "type": "pronoun",
    "english_case": "*",
    "aligned_case": "Acc",
    "english_form": "you",
    "aligned_form": "panie",
    "english_coref_pos": "",
    "aligned_coref_gender": "",
    "aligned_coref_number": "",
    "aligned_coref_pos": "",
    "requires_coref": "false"
  },
  "GEN.FORM.PLUR.FEM": {
    "type": "pronoun",
    "english_case": "*",
    "aligned_case": "Gen",
    "english_form": "you",
    "aligned_form": "pa\u0144",
    "english_coref_pos": "",
    "aligned_coref_gender": "",
    "aligned_coref_number": "",
    "aligned_coref_pos": "",
    "requires_coref": "false"
  },
  "LOC.FORM.PLUR.FEM": {
    "type": "pronoun",
    "english_case": "*",
    "aligned_case": "Loc",
    "english_form": "you",
    "aligned_form": "paniach",
    "english_coref_pos": "",
    "aligned_coref_gender": "",
    "aligned_coref_number": "",
    "aligned_coref_pos": "",
    "requires_coref": "false"
  },
  "DAT.FORM.PLUR.FEM": {
    "type": "pronoun",
    "english_case": "*",
    "aligned_case": "Dat",
    "english_form": "you",
    "aligned_form": "paniom",
    "english_coref_pos": "",
    "aligned_coref_gender": "",
    "aligned_coref_number": "",
    "aligned_coref_pos": "",
    "requires_coref": "false"
  },
  "INS.FORM.PLUR.FEM": {
    "type": "pronoun",
    "english_case": "*",
    "aligned_case": "Ins",
    "english_form": "you",
    "aligned_form": "paniami",
    "english_coref_pos": "",
    "aligned_coref_gender": "",
    "aligned_coref_number": "",
    "aligned_coref_pos": "",
    "requires_coref": "false"
  },
  "NOM.FORM.PLUR.MIXED": {
    "type": "pronoun",
    "english_case": "*",
    "aligned_case": "Nom",
    "english_form": "you",
    "aligned_form": "pa\u0144stwo",
    "english_coref_pos": "",
    "aligned_coref_gender": "",
    "aligned_coref_number": "",
    "aligned_coref_pos": "",
    "requires_coref": "false"
  },
  "ACC.FORM.PLUR.MIXED": {
    "type": "pronoun",
    "english_case": "*",
    "aligned_case": "Acc",
    "english_form": "you",
    "aligned_form": "pa\u0144stwa",
    "english_coref_pos": "",
    "aligned_coref_gender": "",
    "aligned_coref_number": "",
    "aligned_coref_pos": "",
    "requires_coref": "false"
  },
  "GEN.FORM.PLUR.MIXED": {
    "type": "pronoun",
    "english_case": "*",
    "aligned_case": "Gen",
    "english_form": "you",
    "aligned_form": "pa\u0144stwa",
    "english_coref_pos": "",
    "aligned_coref_gender": "",
    "aligned_coref_number": "",
    "aligned_coref_pos": "",
    "requires_coref": "false"
  },
  "LOC.FORM.PLUR.MIXED": {
    "type": "pronoun",
    "english_case": "*",
    "aligned_case": "Loc",
    "english_form": "you",
    "aligned_form": "pa\u0144stwu",
    "english_coref_pos": "",
    "aligned_coref_gender": "",
    "aligned_coref_number": "",
    "aligned_coref_pos": "",
    "requires_coref": "false"
  },
  "DAT.FORM.PLUR.MIXED": {
    "type": "pronoun",
    "english_case": "*",
    "aligned_case": "Dat",
    "english_form": "you",
    "aligned_form": "pa\u0144stwu",
    "english_coref_pos": "",
    "aligned_coref_gender": "",
    "aligned_coref_number": "",
    "aligned_coref_pos": "",
    "requires_coref": "false"
  },
  "INS.FORM.PLUR.MIXED": {
    "type": "pronoun",
    "english_case": "*",
    "aligned_case": "Ins",
    "english_form": "you",
    "aligned_form": "pa\u0144stwem",
    "english_coref_pos": "",
    "aligned_coref_gender": "",
    "aligned_coref_number": "",
    "aligned_coref_pos": "",
    "requires_coref": "false"
  }
}